ancientfiles/__init__.py
ancientfiles/core.py
ancientfiles/images/ancientfiles_doxygen.png
ancientfiles/locale/ancientfiles.pot
ancientfiles/locale/es/LC_MESSAGES/ancientfiles.mo
ancientfiles/locale/es.po
ancientfiles/poethepoet.py
ancientfiles-0.3.0.dist-info/LICENSE
ancientfiles-0.3.0.dist-info/METADATA
ancientfiles-0.3.0.dist-info/WHEEL
ancientfiles-0.3.0.dist-info/entry_points.txt
ancientfiles-0.3.0.dist-info/RECORD
