Metadata-Version: 2.3
Name: ancientfiles
Version: 0.3.0
Summary: Moves ancient files from a directory to another selecting is age. Then you can backup them.
License: GPL-3
Author: turulomio
Author-email: turulomio@yahoo.es
Requires-Python: >=3.11,<4
Classifier: License :: Other/Proprietary License
Classifier: Programming Language :: Python :: 3
Classifier: Programming Language :: Python :: 3.11
Classifier: Programming Language :: Python :: 3.12
Classifier: Programming Language :: Python :: 3.13
